scrapy_twrh/__init__.py
scrapy_twrh/items.py
scrapy_twrh/spiders/__init__.py
scrapy_twrh/spiders/enums.py
scrapy_twrh/spiders/rental591/__init__.py
scrapy_twrh/spiders/rental591/all_591_cities.py
scrapy_twrh/spiders/rental591/detail_mixin.py
scrapy_twrh/spiders/rental591/detail_raw_parser.py
scrapy_twrh/spiders/rental591/list_mixin.py
scrapy_twrh/spiders/rental591/ocr_utils.py
scrapy_twrh/spiders/rental591/playwright_utils.py
scrapy_twrh/spiders/rental591/rental591_spider.py
scrapy_twrh/spiders/rental591/request_generator.py
scrapy_twrh/spiders/rental591/util.py
scrapy_twrh/spiders/rental_spider.py
scrapy_twrh/spiders/tw_regions.json
scrapy_twrh/spiders/util.py
scrapy_tw_rental_house-2.1.7.dist-info/LICENSE
scrapy_tw_rental_house-2.1.7.dist-info/METADATA
scrapy_tw_rental_house-2.1.7.dist-info/WHEEL
scrapy_tw_rental_house-2.1.7.dist-info/RECORD
