Metadata-Version: 2.1
Name: scrapy-tw-rental-house
Version: 2.1.7
Summary: Scrapy spider for TW Rental House
Home-page: https://github.com/g0v/tw-rental-house-data/tree/master/scrapy-tw-rental-house
License: MIT
Author: ddio
Author-email: ddio@ddio.io
Requires-Python: >=3.10,<4.0
Classifier: License :: OSI Approved :: MIT License
Classifier: Programming Language :: Python :: 3
Classifier: Programming Language :: Python :: 3.10
Classifier: Programming Language :: Python :: 3.11
Classifier: Programming Language :: Python :: 3.12
Requires-Dist: Scrapy (>=2.11.0,<3.0.0)
Requires-Dist: numpy (>=2.2.3,<3.0.0)
Requires-Dist: opencv-python (>=4.11.0.86,<5.0.0.0)
Requires-Dist: paddleocr (>=2.10.0,<3.0.0)
Requires-Dist: paddlepaddle (==3.0.0rc1)
Requires-Dist: playwright (>=1.50.0,<2.0.0)
Requires-Dist: scrapy-playwright (>=0.0.42,<0.0.43)
Project-URL: Repository, https://github.com/g0v/tw-rental-house-data/tree/master/scrapy-tw-rental-house
